texpj/__init__.py
texpj/core.py
texpj-1.2.4.dist-info/entry_points.txt
texpj-1.2.4.dist-info/WHEEL
texpj-1.2.4.dist-info/METADATA
texpj-1.2.4.dist-info/RECORD
