Metadata-Version: 2.1
Name: texpj
Version: 1.2.4
Summary: Utilidad para mantener plantillas de latex
Author: Benyamin Galeano
Author-email: benyamin.galeano@galileo.edu
Requires-Python: >=3.8,<4.0
Classifier: Programming Language :: Python :: 3
Classifier: Programming Language :: Python :: 3.10
Classifier: Programming Language :: Python :: 3.8
Classifier: Programming Language :: Python :: 3.9
Requires-Dist: click (>=7.1.2,<8.0.0)
